{
	"animations": [
		{
			"loop": false,
			"offsets": [
				0,
				0
			],
			"anim": "idle",
			"fps": 24,
			"name": "$",
			"indices": []
		},
		{
			"loop": false,
			"offsets": [
				0,
				0
			],
			"anim": "singUP",
			"fps": 24,
			"name": "$",
			"indices": []
		},
		{
			"loop": false,
			"offsets": [
				0,
				0
			],
			"anim": "singLEFT",
			"fps": 24,
			"name": "$",
			"indices": []
		},
		{
			"loop": false,
			"offsets": [
				0,
				0
			],
			"anim": "singRIGHT",
			"fps": 24,
			"name": "$",
			"indices": []
		},
		{
			"loop": false,
			"offsets": [
				0,
				0
			],
			"anim": "singDOWN",
			"fps": 24,
			"name": "$",
			"indices": []
		}
	],
	"no_antialiasing": false,
	"image": "characters/dollarmbi",
	"position": [
		0,
		0
	],
	"healthicon": "_",
	"flip_x": false,
	"healthbar_colors": [
		230,
		224,
		188
	],
	"camera_position": [
		0,
		0
	],
	"sing_duration": 4,
	"scale": 1
}