{
	"animations": [
		{
			"loop": true,
			"offsets": [
				190,
				-230
			],
			"anim": "idle",
			"fps": 24,
			"name": "idle",
			"indices": []
		},
		{
			"loop": false,
			"offsets": [
				405,
				-198
			],
			"anim": "singLEFT",
			"fps": 24,
			"name": "left",
			"indices": []
		},
		{
			"loop": false,
			"offsets": [
				500,
				-227
			],
			"anim": "singRIGHT",
			"fps": 24,
			"name": "right",
			"indices": []
		},
		{
			"loop": false,
			"offsets": [
				377,
				-191
			],
			"anim": "singDOWN",
			"fps": 24,
			"name": "down",
			"indices": []
		},
		{
			"loop": false,
			"offsets": [
				324,
				306
			],
			"anim": "singUP",
			"fps": 24,
			"name": "up",
			"indices": []
		}
	],
	"no_antialiasing": true,
	"image": "characters/nightbambi",
	"position": [
		120,
		-50
	],
	"healthicon": "nightbambi",
	"flip_x": false,
	"healthbar_colors": [
		0,
		255,
		0
	],
	"camera_position": [
		-320,
		220
	],
	"sing_duration": 4,
	"scale": 1
}